lemmatization/__init__.py
lemmatization/lemmatization.py
search_engine_rishatsadykov-1.1.dist-info/LICENSE
search_engine_rishatsadykov-1.1.dist-info/METADATA
search_engine_rishatsadykov-1.1.dist-info/WHEEL
search_engine_rishatsadykov-1.1.dist-info/top_level.txt
search_engine_rishatsadykov-1.1.dist-info/RECORD
