Metadata-Version: 2.1
Name: search-engine-rishatsadykov
Version: 1.1
Summary: Calculates TF-IDF for data set
Home-page: https://github.com/rishat11/information-retrieval
Author: Rishat Sadykov
Author-email: r.sadickov2010@yandex.ru
License: UNKNOWN
Platform: UNKNOWN
Classifier: Programming Language :: Python :: 3.8
Classifier: License :: OSI Approved :: MIT License
Classifier: Operating System :: OS Independent
Requires-Python: >=3.6
Requires-Dist: DAWG-Python (==0.7.2)
Requires-Dist: docopt (==0.6.2)
Requires-Dist: psycopg2 (==2.8.6)
Requires-Dist: pymorphy2 (==0.9.1)
Requires-Dist: pymorphy2-dicts-ru (==2.4.417127.4579844)
